pipelines/__init__.py
pipelines/admin.py
pipelines/apps.py
pipelines/baker_recipes.py
pipelines/base.py
pipelines/config.py
pipelines/forms.py
pipelines/log.py
pipelines/models.py
pipelines/registry.py
pipelines/status.py
pipelines/urls.py
pipelines/utils.py
pipelines/views.py
pipelines/management/__init__.py
pipelines/management/commands/__init__.py
pipelines/management/commands/clear_tasks_and_logs.py
pipelines/management/commands/pipelines.py
pipelines/meta/__init__.py
pipelines/migrations/0001_initial.py
pipelines/migrations/0002_rename_last_run_pipelineexecution_started_and_more.py
pipelines/migrations/0003_alter_pipelineexecution_reporter_and_more.py
pipelines/migrations/0004_alter_pipelineexecution_options_and_more.py
pipelines/migrations/0004_alter_pipelineexecution_status.py
pipelines/migrations/0005_merge_20230103_1354.py
pipelines/migrations/0006_rename_pipelineexecution_pipelineresult_and_more.py
pipelines/migrations/0007_pipelineexecution_taskexecution_and_more.py
pipelines/migrations/0008_auto_20230116_1208.py
pipelines/migrations/0009_remove_pipelineresult_pipeline_id_and_more.py
pipelines/migrations/0010_remove_taskexecution_pipeline_and_more.py
pipelines/migrations/0011_alter_taskresult_status.py
pipelines/migrations/0012_remove_taskresult_pipeline_task_and_more.py
pipelines/migrations/0013_pipelineexecution_completed_pipelineresult_completed_and_more.py
pipelines/migrations/0014_remove_pipelineresult_input_data_and_more.py
pipelines/migrations/0015_delete_tasklog_pipelinelog_context_id_and_more.py
pipelines/migrations/0016_alter_pipelineexecution_run_id.py
pipelines/migrations/0017_alter_pipelineexecution_run_id.py
pipelines/migrations/0018_rename_pipelineexecution_ormpipelineexecution_and_more.py
pipelines/migrations/0019_alter_ormpipelineexecution_completed_and_more.py
pipelines/migrations/0020_delete_valuestore_alter_pipelinelog_context_type.py
pipelines/migrations/__init__.py
pipelines/reporters/__init__.py
pipelines/reporters/base.py
django_pipelines-0.1.1.dist-info/LICENSE
django_pipelines-0.1.1.dist-info/METADATA
django_pipelines-0.1.1.dist-info/WHEEL
django_pipelines-0.1.1.dist-info/top_level.txt
django_pipelines-0.1.1.dist-info/RECORD
