Metadata-Version: 2.1
Name: django-pipelines
Version: 0.1.1
Summary: Tools for building data pipelines with Django
Home-page: https://github.com/wildfish/django-pipelines
Author: Wildfish
Author-email: developers@wildfish.com
License: BSD-3-Clause
Platform: UNKNOWN
Classifier: Development Status :: 3 - Alpha
Classifier: Environment :: Web Environment
Classifier: Intended Audience :: Developers
Classifier: License :: OSI Approved :: BSD License
Classifier: Operating System :: OS Independent
Classifier: Programming Language :: Python :: 3
Classifier: Programming Language :: Python :: 3.9
Classifier: Programming Language :: Python :: 3.10
Classifier: Programming Language :: Python :: 3.11
Classifier: Framework :: Django
Classifier: Framework :: Django :: 3.2
Classifier: Framework :: Django :: 4.0
Classifier: Framework :: Django :: 4.1
Requires-Python: >=3.9
License-File: LICENSE
Requires-Dist: Django (>=3.2)
Requires-Dist: django-extensions
Requires-Dist: celery
Requires-Dist: pydantic
